challengeutils/__init__.py
challengeutils/__main__.py
challengeutils/__version__.py
challengeutils/annotations.py
challengeutils/challenge.py
challengeutils/cheat_detection.py
challengeutils/create_portal_challenge.py
challengeutils/createchallenge.py
challengeutils/discussion.py
challengeutils/dockertools.py
challengeutils/evaluation_queue.py
challengeutils/mirrorwiki.py
challengeutils/permissions.py
challengeutils/submission.py
challengeutils/teams.py
challengeutils/utils.py
challengeutils/wiki.py
challengeutils/synapseservices/__init__.py
challengeutils/synapseservices/base_service.py
challengeutils/synapseservices/challenge.py
challengeutils/synapseservices/discussion.py
challengeutils-4.3.0.data/scripts/runqueue.py
scoring_harness/__init__.py
scoring_harness/base_processor.py
scoring_harness/exceptions.py
scoring_harness/lock.py
scoring_harness/messages.py
scoring_harness/queue_scorer.py
scoring_harness/queue_validator.py
tests/__init__.py
tests/evaluation_queue.py
tests/test_annotations.py
tests/test_challenge.py
tests/test_cheatdetection.py
tests/test_createchallenge.py
tests/test_discussion.py
tests/test_dockertools.py
tests/test_evaluation_queue.py
tests/test_mirrorwiki.py
tests/test_permissions.py
tests/test_processor.py
tests/test_scorer.py
tests/test_submission.py
tests/test_teams.py
tests/test_utils.py
tests/test_validator.py
tests/test_wiki.py
challengeutils-4.3.0.dist-info/LICENSE
challengeutils-4.3.0.dist-info/METADATA
challengeutils-4.3.0.dist-info/WHEEL
challengeutils-4.3.0.dist-info/entry_points.txt
challengeutils-4.3.0.dist-info/top_level.txt
challengeutils-4.3.0.dist-info/RECORD
