Metadata-Version: 2.1
Name: challengeutils
Version: 4.3.0
Summary: Challenge utility functions
Home-page: https://github.com/Sage-Bionetworks/challengeutils
Author: Thomas Yu
Author-email: thomas.yu@sagebionetworks.org
License: Apache
Project-URL: Bug Tracker, https://github.com/Sage-Bionetworks/challengeutils/issues
Project-URL: Source Code, https://github.com/Sage-Bionetworks/challengeutil
Project-URL: Documentation, https://sage-bionetworks.github.io/challengeutils/
Platform: any
Classifier: Development Status :: 5 - Production/Stable
Classifier: Programming Language :: Python
Classifier: Programming Language :: Python :: 3.8
Classifier: Programming Language :: Python :: 3.9
Classifier: Programming Language :: Python :: 3.10
Classifier: Programming Language :: Python :: 3.11
Classifier: Programming Language :: Python :: 3.12
Classifier: Operating System :: MacOS
Classifier: Operating System :: Microsoft :: Windows
Classifier: Operating System :: Unix
Classifier: Operating System :: POSIX :: Linux
Classifier: Intended Audience :: Developers
Classifier: Intended Audience :: Science/Research
Classifier: License :: OSI Approved :: Apache Software License
Classifier: Topic :: Software Development :: Libraries
Classifier: Topic :: Scientific/Engineering
Classifier: Topic :: Scientific/Engineering :: Bio-Informatics
Requires-Python: <=3.12,>3.7
License-File: LICENSE
Requires-Dist: pandas >=1.1.5
Requires-Dist: requests
Requires-Dist: synapseclient >=2.6.0
Requires-Dist: tabulate >=0.9.0
Requires-Dist: jellyfish >=0.9.0
Requires-Dist: scipy >=1.7.0
